[
    {
        "id": 0,
        "starttime": 0,
        "endtime": 564,
        "column": 2
    },
    {
        "id": 1,
        "starttime": 565,
        "endtime": 1427,
        "column": 4
    },
    {
        "id": 2,
        "starttime": 1428,
        "endtime": 1669,
        "column": 5
    },
    {
        "id": 3,
        "starttime": 1670,
        "endtime": 1684,
        "column": 1
    },
    {
        "id": 4,
        "starttime": 1685,
        "endtime": 3884,
        "column": 6
    },
    {
        "id": 5,
        "starttime": 3885,
        "endtime": 4750,
        "column": 5
    },
    {
        "id": 6,
        "starttime": 4751,
        "endtime": 4890,
        "column": 1
    },
    {
        "id": 7,
        "starttime": 4891,
        "endtime": 6491,
        "column": 0
    },
    {
        "id": 8,
        "starttime": 6492,
        "endtime": 6529,
        "column": 1
    },
    {
        "id": 9,
        "starttime": 6530,
        "endtime": 6731,
        "column": 0
    },
    {
        "id": 10,
        "starttime": 6732,
        "endtime": 7000,
        "column": 1
    },
    {
        "id": 11,
        "starttime": 7001,
        "endtime": 7100,
        "column": 3
    },
    {
        "id": 12,
        "starttime": 7101,
        "endtime": 7198,
        "column": 0
    },
    {
        "id": 13,
        "starttime": 7199,
        "endtime": 11222,
        "column": 3
    },
    {
        "id": 14,
        "starttime": 11223,
        "endtime": 11376,
        "column": 1
    },
    {
        "id": 15,
        "starttime": 11377,
        "endtime": 12789,
        "column": 0
    },
    {
        "id": 16,
        "starttime": 12790,
        "endtime": 13413,
        "column": 1
    },
    {
        "id": 17,
        "starttime": 13414,
        "endtime": 15089,
        "column": 3
    },
    {
        "id": 18,
        "starttime": 15090,
        "endtime": 16127,
        "column": 1
    },
    {
        "id": 19,
        "starttime": 16128,
        "endtime": 17260,
        "column": 3
    },
    {
        "id": 20,
        "starttime": 17261,
        "endtime": 18781,
        "column": 1
    },
    {
        "id": 21,
        "starttime": 18782,
        "endtime": 20775,
        "column": 5
    },
    {
        "id": 22,
        "starttime": 20776,
        "endtime": 22933,
        "column": 3
    },
    {
        "id": 23,
        "starttime": 22934,
        "endtime": 23131,
        "column": 1
    },
    {
        "id": 24,
        "starttime": 23132,
        "endtime": 24926,
        "column": 0
    },
    {
        "id": 25,
        "starttime": 24927,
        "endtime": 25073,
        "column": 1
    },
    {
        "id": 26,
        "starttime": 25075,
        "endtime": 25079,
        "column": 0
    },
    {
        "id": 27,
        "starttime": 25080,
        "endtime": 25463,
        "column": 1
    },
    {
        "id": 28,
        "starttime": 25464,
        "endtime": 25561,
        "column": 3
    },
    {
        "id": 29,
        "starttime": 25562,
        "endtime": 25624,
        "column": 1
    },
    {
        "id": 30,
        "starttime": 25625,
        "endtime": 26271,
        "column": 3
    },
    {
        "id": 31,
        "starttime": 26274,
        "endtime": 26279,
        "column": 0
    },
    {
        "id": 32,
        "starttime": 26280,
        "endtime": 26355,
        "column": 3
    },
    {
        "id": 33,
        "starttime": 26356,
        "endtime": 26907,
        "column": 0
    },
    {
        "id": 34,
        "starttime": 26908,
        "endtime": 27756,
        "column": 1
    },
    {
        "id": 35,
        "starttime": 27757,
        "endtime": 27862,
        "column": 0
    },
    {
        "id": 36,
        "starttime": 27863,
        "endtime": 28119,
        "column": 3
    },
    {
        "id": 37,
        "starttime": 28120,
        "endtime": 28160,
        "column": 0
    },
    {
        "id": 38,
        "starttime": 28161,
        "endtime": 28191,
        "column": 3
    },
    {
        "id": 39,
        "starttime": 28192,
        "endtime": 29101,
        "column": 0
    },
    {
        "id": 40,
        "starttime": 29102,
        "endtime": 29572,
        "column": 1
    },
    {
        "id": 41,
        "starttime": 29573,
        "endtime": 30491,
        "column": 6
    },
    {
        "id": 42,
        "starttime": 30492,
        "endtime": 30587,
        "column": 5
    },
    {
        "id": 43,
        "starttime": 30588,
        "endtime": 33971,
        "column": 7
    },
    {
        "id": 44,
        "starttime": 33972,
        "endtime": 34117,
        "column": 1
    },
    {
        "id": 45,
        "starttime": 34118,
        "endtime": 36094,
        "column": 3
    },
    {
        "id": 46,
        "starttime": 36095,
        "endtime": 36124,
        "column": 1
    },
    {
        "id": 47,
        "starttime": 36125,
        "endtime": 36130,
        "column": 3
    },
    {
        "id": 48,
        "starttime": 36131,
        "endtime": 36139,
        "column": 1
    },
    {
        "id": 49,
        "starttime": 36140,
        "endtime": 36184,
        "column": 3
    },
    {
        "id": 50,
        "starttime": 36185,
        "endtime": 36195,
        "column": 1
    },
    {
        "id": 51,
        "starttime": 36196,
        "endtime": 36229,
        "column": 3
    },
    {
        "id": 52,
        "starttime": 36230,
        "endtime": 36435,
        "column": 1
    },
    {
        "id": 53,
        "starttime": 36436,
        "endtime": 36449,
        "column": 3
    },
    {
        "id": 54,
        "starttime": 36453,
        "endtime": 37852,
        "column": 3
    },
    {
        "id": 55,
        "starttime": 37853,
        "endtime": 37900,
        "column": 1
    },
    {
        "id": 56,
        "starttime": 37901,
        "endtime": 37912,
        "column": 0
    },
    {
        "id": 57,
        "starttime": 37913,
        "endtime": 38305,
        "column": 1
    },
    {
        "id": 58,
        "starttime": 38306,
        "endtime": 40822,
        "column": 5
    },
    {
        "id": 59,
        "starttime": 40823,
        "endtime": 43216,
        "column": 1
    },
    {
        "id": 60,
        "starttime": 43217,
        "endtime": 44430,
        "column": 3
    },
    {
        "id": 61,
        "starttime": 44431,
        "endtime": 45434,
        "column": 1
    },
    {
        "id": 62,
        "starttime": 45435,
        "endtime": 46508,
        "column": 3
    },
    {
        "id": 63,
        "starttime": 46510,
        "endtime": 46515,
        "column": 1
    },
    {
        "id": 64,
        "starttime": 46516,
        "endtime": 46519,
        "column": 3
    },
    {
        "id": 65,
        "starttime": 46520,
        "endtime": 47786,
        "column": 1
    },
    {
        "id": 66,
        "starttime": 47787,
        "endtime": 49141,
        "column": 0
    },
    {
        "id": 67,
        "starttime": 49142,
        "endtime": 49564,
        "column": 1
    },
    {
        "id": 68,
        "starttime": 49565,
        "endtime": 49851,
        "column": 5
    },
    {
        "id": 69,
        "starttime": 49852,
        "endtime": 51277,
        "column": 4
    },
    {
        "id": 70,
        "starttime": 51278,
        "endtime": 51940,
        "column": 2
    }
]