[
    {
        "id": 0,
        "starttime": 0,
        "endtime": 636,
        "column": 4
    },
    {
        "id": 1,
        "starttime": 637,
        "endtime": 2941,
        "column": 0
    },
    {
        "id": 2,
        "starttime": 2942,
        "endtime": 5408,
        "column": 3
    },
    {
        "id": 3,
        "starttime": 5409,
        "endtime": 7153,
        "column": 1
    },
    {
        "id": 4,
        "starttime": 7154,
        "endtime": 7424,
        "column": 3
    },
    {
        "id": 5,
        "starttime": 7425,
        "endtime": 7469,
        "column": 5
    },
    {
        "id": 6,
        "starttime": 7470,
        "endtime": 7474,
        "column": 3
    },
    {
        "id": 7,
        "starttime": 7475,
        "endtime": 7478,
        "column": 5
    },
    {
        "id": 8,
        "starttime": 7479,
        "endtime": 7483,
        "column": 3
    },
    {
        "id": 9,
        "starttime": 7484,
        "endtime": 10821,
        "column": 5
    },
    {
        "id": 10,
        "starttime": 10822,
        "endtime": 12877,
        "column": 0
    },
    {
        "id": 11,
        "starttime": 12878,
        "endtime": 13165,
        "column": 5
    },
    {
        "id": 12,
        "starttime": 13166,
        "endtime": 14124,
        "column": 1
    },
    {
        "id": 13,
        "starttime": 14125,
        "endtime": 15391,
        "column": 3
    },
    {
        "id": 14,
        "starttime": 15392,
        "endtime": 17094,
        "column": 1
    },
    {
        "id": 15,
        "starttime": 17095,
        "endtime": 17302,
        "column": 3
    },
    {
        "id": 16,
        "starttime": 17303,
        "endtime": 17310,
        "column": 5
    },
    {
        "id": 17,
        "starttime": 17314,
        "endtime": 20204,
        "column": 5
    },
    {
        "id": 18,
        "starttime": 20205,
        "endtime": 20763,
        "column": 3
    },
    {
        "id": 19,
        "starttime": 20764,
        "endtime": 20824,
        "column": 1
    },
    {
        "id": 20,
        "starttime": 20825,
        "endtime": 25821,
        "column": 2
    },
    {
        "id": 21,
        "starttime": 25822,
        "endtime": 27056,
        "column": 6
    },
    {
        "id": 22,
        "starttime": 27057,
        "endtime": 28303,
        "column": 7
    },
    {
        "id": 23,
        "starttime": 28304,
        "endtime": 36089,
        "column": 0
    },
    {
        "id": 24,
        "starttime": 36090,
        "endtime": 36788,
        "column": 4
    }
]